LICENSE
MANIFEST.in
README.md
setup.py
restapisdk/__init__.py
restapisdk/api_helper.py
restapisdk/configuration.py
restapisdk/decorators.py
restapisdk/restapisdk_client.py
restapisdk.egg-info/PKG-INFO
restapisdk.egg-info/SOURCES.txt
restapisdk.egg-info/dependency_links.txt
restapisdk.egg-info/requires.txt
restapisdk.egg-info/top_level.txt
restapisdk/controllers/__init__.py
restapisdk/controllers/admin_controller.py
restapisdk/controllers/base_controller.py
restapisdk/controllers/connection_controller.py
restapisdk/controllers/data_controller.py
restapisdk/controllers/database_controller.py
restapisdk/controllers/group_controller.py
restapisdk/controllers/metadata_controller.py
restapisdk/controllers/session_controller.py
restapisdk/controllers/user_controller.py
restapisdk/exceptions/__init__.py
restapisdk/exceptions/api_exception.py
restapisdk/exceptions/error_response_exception.py
restapisdk/http/__init__.py
restapisdk/http/http_call_back.py
restapisdk/http/http_client.py
restapisdk/http/http_method_enum.py
restapisdk/http/http_request.py
restapisdk/http/http_response.py
restapisdk/http/requests_client.py
restapisdk/http/auth/__init__.py
restapisdk/http/auth/o_auth_2.py
restapisdk/models/__init__.py
restapisdk/models/access_enum.py
restapisdk/models/access_level_input.py
restapisdk/models/add_table_input.py
restapisdk/models/adminsync_principal_response.py
restapisdk/models/analyst_onboarding_complete_enum.py
restapisdk/models/api_rest_v_2_admin_changeowner_request.py
restapisdk/models/api_rest_v_2_admin_configuration_update_request.py
restapisdk/models/api_rest_v_2_admin_resetpassword_request.py
restapisdk/models/api_rest_v_2_admin_syncprincipal_request.py
restapisdk/models/api_rest_v_2_connection_addtable_request.py
restapisdk/models/api_rest_v_2_connection_create_request.py
restapisdk/models/api_rest_v_2_connection_removetable_request.py
restapisdk/models/api_rest_v_2_connection_search_request.py
restapisdk/models/api_rest_v_2_connection_update_request.py
restapisdk/models/api_rest_v_2_data_answer_request.py
restapisdk/models/api_rest_v_2_data_liveboard_request.py
restapisdk/models/api_rest_v_2_data_search_request.py
