Metadata-Version: 2.1
Name: restapisdk
Version: 2.0.0
Summary: Python client library for RESTAPI SDK
Home-page: https://apimatic.io
Author: APIMatic SDK Generator
Author-email: support@apimatic.io
License: UNKNOWN
Platform: UNKNOWN
